xarray_enmap/__init__.py
xarray_enmap/cli.py
xarray_enmap/xarray_enmap.py
xarray_enmap-0.0.3.dist-info/licenses/LICENSE
xarray_enmap-0.0.3.dist-info/METADATA
xarray_enmap-0.0.3.dist-info/WHEEL
xarray_enmap-0.0.3.dist-info/entry_points.txt
xarray_enmap-0.0.3.dist-info/top_level.txt
xarray_enmap-0.0.3.dist-info/RECORD
