Metadata-Version: 2.4
Name: xarray-enmap
Version: 0.0.3
Summary: xarray backend for EnMAP data archives
Author-email: Pontus Lurcock <pontus.lurcock@brockmann-consult.de>
License-Expression: MIT
Project-URL: Documentation, https://github.com/bcdev/xarray-enmap/blob/main/README.md
Project-URL: Issues, https://github.com/bcdev/xarray-enmap/issues
Project-URL: Changelog, https://github.com/bcdev/xarray-enmap/blob/main/CHANGES.md
Project-URL: Repository, https://github.com/bcdev/xarray-enmap
Project-URL: Homepage, https://github.com/bcdev/xarray-enmap
Keywords: analysis ready data,data science,datacube,xarray,zarr
Classifier: Programming Language :: Python :: 3
Classifier: Operating System :: OS Independent
Classifier: Development Status :: 5 - Production/Stable
Classifier: Topic :: Scientific/Engineering
Requires-Python: >=3.11
License-File: LICENSE
Requires-Dist: fsspec
Requires-Dist: rioxarray
Requires-Dist: shapely
Requires-Dist: xarray
Provides-Extra: dev
Requires-Dist: pytest; extra == "dev"
Requires-Dist: pytest-cov; extra == "dev"
Requires-Dist: black; extra == "dev"
Requires-Dist: flake8; extra == "dev"
Provides-Extra: doc
Requires-Dist: mkdocs; extra == "doc"
Requires-Dist: mkdocs-material; extra == "doc"
Requires-Dist: mkdocstrings; extra == "doc"
Requires-Dist: mkdocstrings-python; extra == "doc"
Provides-Extra: zarr
Requires-Dist: zarr; extra == "zarr"
Requires-Dist: numcodecs; extra == "zarr"
Dynamic: license-file
